cryptonite/Caesar.py
cryptonite/Otp.py
cryptonite/Rsa.py
cryptonite/__init__.py
cryptonite-0.0.5.dist-info/LICENSE
cryptonite-0.0.5.dist-info/METADATA
cryptonite-0.0.5.dist-info/WHEEL
cryptonite-0.0.5.dist-info/top_level.txt
cryptonite-0.0.5.dist-info/RECORD
